factorial_aivn_khoapd/__init__.py
factorial_aivn_khoapd/app.py
factorial_aivn_khoapd/factorial.py
factorial_aivn_khoapd-0.1.0.dist-info/METADATA
factorial_aivn_khoapd-0.1.0.dist-info/WHEEL
factorial_aivn_khoapd-0.1.0.dist-info/RECORD
