Metadata-Version: 2.1
Name: factorial-aivn-khoapd
Version: 0.1.0
Summary: 
Author: khoapd
Author-email: khoa.phamdangaio97@gmail.com
Requires-Python: >=3.11,<4.0
Classifier: Programming Language :: Python :: 3
Classifier: Programming Language :: Python :: 3.11
Classifier: Programming Language :: Python :: 3.12
Requires-Dist: streamlit (>=1.32.2,<2.0.0)
